HexBug/data/__init__.py
HexBug/data/book.py
HexBug/data/exceptions.py
HexBug/data/hex_math.py
HexBug/data/lookups.py
HexBug/data/mods.py
HexBug/data/patterns.py
HexBug/data/py.typed
HexBug/data/registry.py
HexBug/data/sources.py
HexBug/data/special_handlers.py
HexBug/data/static_data.py
HexBug/data/parsers/__init__.py
HexBug/data/parsers/ast.py
HexBug/data/parsers/helpers.py
HexBug/data/parsers/pretty_print.py
HexBug/data/parsers/reveal.lark
HexBug/data/parsers/reveal.py
HexBug/data/utils/__init__.py
HexBug/data/utils/collections.py
HexBug/data/utils/enums.py
HexBug/data/utils/hexdoc.py
HexBug/data/utils/shorthand.py
HexBug/data/utils/strings.py
hexbug_data-2.7.4.dist-info/METADATA
hexbug_data-2.7.4.dist-info/WHEEL
hexbug_data-2.7.4.dist-info/RECORD
